spark_analyzer/README.md
spark_analyzer/__init__.py
spark_analyzer/cli.py
spark_analyzer/config_cli.py
spark_analyzer/local_acceleration_analyzer.py
spark_analyzer/lib/__init__.py
spark_analyzer/lib/api_client.py
spark_analyzer/lib/s3_uploader.py
spark_analyzer/lib/spark_stage_analyzer.py
spark_analyzer/local_analysis/__init__.py
spark_analyzer/local_analysis/data_models.py
spark_analyzer/local_analysis/local_acceleration_analyzer.py
spark_analyzer/local_analysis/metrics_analyzer.py
spark_analyzer/local_analysis/report_generator.py
spark_analyzer/local_analysis/workflow_classifier.py
spark_analyzer/resources/storage_format_keywords.json
spark_analyzer/resources/workflow_type_keywords.json
spark_analyzer/resources/test_data/stage_analyzer_test_data.json
spark_analyzer/static/images/sample_spark_analysis_report.png
spark_analyzer/tests/__init__.py
spark_analyzer/tests/test_cookie_utils.py
spark_analyzer/tests/test_spark_stage_analyzer.py
spark_analyzer/utils/__init__.py
spark_analyzer/utils/formatting.py
spark_analyzer-0.1.30.dist-info/METADATA
spark_analyzer-0.1.30.dist-info/WHEEL
spark_analyzer-0.1.30.dist-info/entry_points.txt
spark_analyzer-0.1.30.dist-info/top_level.txt
spark_analyzer-0.1.30.dist-info/RECORD
